tut_autogen/t10_coworker/coworker.py
tut_autogen/t10_coworker/coworker_solver.py
tut_autogen/t10_sqlite_mcp/nssm-2.24.zip
tut_autogen/t10_sqlite_mcp/nssm_readme.txt
tut_autogen/t10_sqlite_mcp/question_generator.py
tut_autogen/t10_sqlite_mcp/sqlite_mcp_server.py
tut_autogen/t10_sqlite_mcp/student_data_generator.py
tut_autogen/t10_sqlite_mcp/student_database.db
tut_autogen/t1_chat_area_autogen_mcp/autogen_deepseek_mcp_chat.py
tut_autogen/t1_chat_area_autogen_mcp/mcp_server_greet_circle_area.py
tut_autogen/t2_deepseek_circle_area/autogen_code_circle_query.py
tut_autogen/t3_multi_agent_geometry_calculation/multi_agent_geometry_calculation.py
tut_autogen/t4_multi_agent_orchestration/multi_agent_orchestration.py
tut_autogen/t5_multi_agent_conditional_orchestration/multi_agent_conditional_orchestration.py
tut_autogen/t6_model_response_evaluation/model_response_evaluation.csv
tut_autogen/t6_model_response_evaluation/model_response_evaluation.py
tut_autogen/t6_model_response_evaluation/model_response_evaluation_result.csv
tut_autogen/t6_model_response_evaluation/model_response_evaluation_result_parser.py
tut_autogen/t6_model_response_evaluation/prompts.py
tut_autogen/t7_autogen_studio/alembic/env.py
tut_autogen/t7_autogen_studio/alembic/README
tut_autogen/t7_autogen_studio/alembic/script.py.mako
tut_autogen/t7_autogen_studio/alembic/versions/6c5e69ea5747_current_schema.py
tut_autogen/t7_autogen_studio/alembic.ini
tut_autogen/t8_ground_truth_generator/ground_truth_generator.py
tut_autogen/t8_ground_truth_generator/ground_truth_generator_sync.py
tut_autogen/t8_ground_truth_generator/promopts.py
tut_autogen/t9_magentic_one/autogen_magentic_one.md
tut_autogen/t9_magentic_one/autogen_magentic_one.py
tut_autogen-0.2.3.dist-info/entry_points.txt
tut_autogen-0.2.3.dist-info/METADATA
tut_autogen-0.2.3.dist-info/WHEEL
tut_autogen-0.2.3.dist-info/RECORD
