Metadata-Version: 2.3
Name: tut-autogen
Version: 0.2.3
Summary: 一个使用AutoGen框架的多智能体编排教程项目，演示如何创建和协调多个AI智能体完成复杂任务
Author: leebin
Author-email: xjd.binlee@qq.com
Requires-Python: >=3.12
Classifier: Programming Language :: Python :: 3
Classifier: Programming Language :: Python :: 3.12
Classifier: Programming Language :: Python :: 3.13
Requires-Dist: autogen (>=0.9.2)
Requires-Dist: autogen-agentchat (>=0.5.7)
Requires-Dist: autogen-ext (>=0.5.7)
Requires-Dist: faker (>=37.4.0)
Requires-Dist: fastmcp (>=2.8.1)
Requires-Dist: loguru (>=0.7.3)
Requires-Dist: mcp (>=1.9.4)
Requires-Dist: openai (>=1.88.0)
Requires-Dist: pandas (>=2.3.0)
